{
	"credit": "Made with Blockbench",
	"textures": {
		"7": "realistic_bakery_products:block/raw_cake/raw_cake/cake_top",
		"8": "realistic_bakery_products:block/raw_cake/raw_cake/cake_inner",
		"9": "realistic_bakery_products:block/raw_cake/raw_cake/cake_side",
		"particle": "realistic_bakery_products:block/raw_cake/raw_cake/cake_top",
		"bottom": "realistic_bakery_products:block/raw_cake/raw_cake_bottom"
	},
	"elements": [
		{
			"from": [3, 0, 1],
			"to": [15, 8, 15],
			"faces": {
				"north": {"uv": [1, 8, 13, 16], "texture": "#9"},
				"east": {"uv": [1, 8, 15, 16], "texture": "#9"},
				"south": {"uv": [3, 8, 15, 16], "texture": "#9"},
				"west": {"uv": [1, 8, 15, 16], "texture": "#8"},
				"up": {"uv": [3, 1, 15, 15], "texture": "#7"},
				"down": {"uv": [3, 1, 15, 15], "texture": "#bottom", "cullface": "down"}
			}
		}
	]
}